module/__init__.py
module/add.py
module/substract.py
module/extras/__init__.py
module/extras/divide.py
module/extras/multiple.py
sample_module/__init__.py
sample_module/add.py
sample_module/substract.py
sample_module/extras/__init__.py
sample_module/extras/divide.py
sample_module/extras/multiple.py
verysimplemodule/__init__.py
verysimplemodule/add.py
verysimplemodule/substract.py
verysimplemodule/extras/__init__.py
verysimplemodule/extras/divide.py
verysimplemodule/extras/multiple.py
verysimplesamplemodule/__init__.py
verysimplesamplemodule/add.py
verysimplesamplemodule/substract.py
verysimplesamplemodule/extras/__init__.py
verysimplesamplemodule/extras/divide.py
verysimplesamplemodule/extras/multiple.py
verysimplesamplemodule/tests/__init__.py
verysimplesamplemodule/tests/test_substract.py
verysimplesamplemodule-0.0.2.dist-info/METADATA
verysimplesamplemodule-0.0.2.dist-info/WHEEL
verysimplesamplemodule-0.0.2.dist-info/top_level.txt
verysimplesamplemodule-0.0.2.dist-info/RECORD
