Metadata-Version: 2.1
Name: verysimplesamplemodule
Version: 0.0.2
Summary: A simple package to understand how to create a package
Author: Myself
Author-email: <email@email.com>
Keywords: python,package
Classifier: Development Status :: 3 - Alpha
Classifier: Intended Audience :: Developers
Classifier: Programming Language :: Python :: 3
Classifier: Operating System :: MacOS :: MacOS X
Classifier: Operating System :: Microsoft :: Windows
